odoo/addons/ssi_general_audit_worksheet_preliminary_analytic_procedure/README.rst
odoo/addons/ssi_general_audit_worksheet_preliminary_analytic_procedure/__init__.py
odoo/addons/ssi_general_audit_worksheet_preliminary_analytic_procedure/__manifest__.py
odoo/addons/ssi_general_audit_worksheet_preliminary_analytic_procedure/data/general_audit_worksheet_type_data.xml
odoo/addons/ssi_general_audit_worksheet_preliminary_analytic_procedure/data/approval_template/general_audit_ws_b32655a.xml
odoo/addons/ssi_general_audit_worksheet_preliminary_analytic_procedure/data/approval_template/general_audit_ws_c8740d4.xml
odoo/addons/ssi_general_audit_worksheet_preliminary_analytic_procedure/data/approval_template/general_audit_ws_d4289e4.xml
odoo/addons/ssi_general_audit_worksheet_preliminary_analytic_procedure/data/ir_sequence/general_audit_ws_b32655a.xml
odoo/addons/ssi_general_audit_worksheet_preliminary_analytic_procedure/data/ir_sequence/general_audit_ws_c8740d4.xml
odoo/addons/ssi_general_audit_worksheet_preliminary_analytic_procedure/data/ir_sequence/general_audit_ws_d4289e4.xml
odoo/addons/ssi_general_audit_worksheet_preliminary_analytic_procedure/data/policy_template/general_audit_ws_b32655a.xml
odoo/addons/ssi_general_audit_worksheet_preliminary_analytic_procedure/data/policy_template/general_audit_ws_c8740d4.xml
odoo/addons/ssi_general_audit_worksheet_preliminary_analytic_procedure/data/policy_template/general_audit_ws_d4289e4.xml
odoo/addons/ssi_general_audit_worksheet_preliminary_analytic_procedure/data/sequence_template/general_audit_ws_b32655a.xml
odoo/addons/ssi_general_audit_worksheet_preliminary_analytic_procedure/data/sequence_template/general_audit_ws_c8740d4.xml
odoo/addons/ssi_general_audit_worksheet_preliminary_analytic_procedure/data/sequence_template/general_audit_ws_d4289e4.xml
odoo/addons/ssi_general_audit_worksheet_preliminary_analytic_procedure/models/__init__.py
odoo14_addon_ssi_general_audit_worksheet_preliminary_analytic_procedure-14.0.1.0.0.dist-info/METADATA
odoo14_addon_ssi_general_audit_worksheet_preliminary_analytic_procedure-14.0.1.0.0.dist-info/WHEEL
odoo14_addon_ssi_general_audit_worksheet_preliminary_analytic_procedure-14.0.1.0.0.dist-info/top_level.txt
odoo14_addon_ssi_general_audit_worksheet_preliminary_analytic_procedure-14.0.1.0.0.dist-info/RECORD
